pypixiv/__init__.py
pypixiv/abc.py
pypixiv/client.py
pypixiv/http.py
pypixiv/py.typed
pypixiv/illust/__init__.py
pypixiv/illust/body.py
pypixiv/illust/item.py
pypixiv/illust/model.py
pypixiv/ranking/__init__.py
pypixiv/ranking/body.py
pypixiv/ranking/item.py
pypixiv/ranking/model.py
pypixiv/user/__init__.py
pypixiv/user/body.py
pypixiv/user/item.py
pypixiv/user/model.py
tests/__init__.py
tests/conftest.py
tests/test_illust.py
tests/test_user.py
tests/util.py
pypixiv-0.2.5.dist-info/LICENCE
pypixiv-0.2.5.dist-info/METADATA
pypixiv-0.2.5.dist-info/WHEEL
pypixiv-0.2.5.dist-info/top_level.txt
pypixiv-0.2.5.dist-info/RECORD
