Metadata-Version: 2.1
Name: pypixiv
Version: 0.2.5
Summary: Pixiv ajax wrapper
Home-page: https://github.com/Saebasol/pypixiv
Author: Ryu JuHeon
Author-email: SaidBySolo@gmail.com
License: UNKNOWN
Platform: UNKNOWN
Requires-Python: >=3.9
License-File: LICENCE
